README.rst
setup.cfg
setup.py
ddict/__init__.py
ddict/ddict.py
ddict.egg-info/PKG-INFO
ddict.egg-info/SOURCES.txt
ddict.egg-info/dependency_links.txt
ddict.egg-info/requires.txt
ddict.egg-info/top_level.txt