Metadata-Version: 1.1
Name: ddict
Version: 0.1.3
Summary: Dict class with dot notation (like attributes) for accessing nested values
Home-page: https://github.com/rbehzadan/ddict
Author: Reza Behzadan
Author-email: rbehzadan@gmail.com
License: MIT
Keywords: dict dot notation access
Platform: UNKNOWN
Classifier: Development Status :: 2 - Pre-Alpha
Classifier: Intended Audience :: Developers
Classifier: Operating System :: OS Independent
Classifier: License :: OSI Approved :: MIT License
Classifier: Programming Language :: Python :: 3.5
Classifier: Programming Language :: Python :: 3.6
